pyhull/__init__.py
pyhull/_pyhull.cpython-37m-darwin.so
pyhull/convex_hull.py
pyhull/delaunay.py
pyhull/halfspace.py
pyhull/simplex.py
pyhull/voronoi.py
pyhull/tests/__init__.py
pyhull/tests/test_convex_hull.py
pyhull/tests/test_delaunay.py
pyhull/tests/test_func.py
pyhull/tests/test_halfspace.py
pyhull/tests/test_simplex.py
pyhull/tests/test_voronoi.py
pyhull-2015.2.1.dist-info/METADATA
pyhull-2015.2.1.dist-info/RECORD
pyhull-2015.2.1.dist-info/WHEEL
pyhull-2015.2.1.dist-info/top_level.txt
