Metadata-Version: 2.1
Name: pyhull
Version: 2015.2.1
Summary: A Python wrapper to Qhull (http://www.qhull.org/) for the computation of the convex hull, Delaunay triangulation and Voronoi diagram
Home-page: https://github.com/materialsvirtuallab/pyhull
Author: Shyue Ping Ong, William Davidson Richards
Author-email: shyuep@gmail.com, wrichard@mit.edu
Maintainer: Shyue Ping Ong
License: MIT
Keywords: qhull,convex,hull,computational,geometry,delaunay,triangulation,voronoi,diagram
Platform: UNKNOWN
Classifier: Programming Language :: Python :: 2
Classifier: Programming Language :: Python :: 2.7
Classifier: Programming Language :: Python :: 3
Classifier: Programming Language :: Python :: 3.2
Classifier: Programming Language :: Python :: 3.3
Classifier: Programming Language :: Python :: 3.4
Classifier: Programming Language :: Python :: 3.5
Classifier: Programming Language :: Python :: 3.6
Classifier: Programming Language :: Python :: 3.7
Classifier: Development Status :: 5 - Production/Stable
Classifier: Intended Audience :: Science/Research
Classifier: License :: OSI Approved :: MIT License
Classifier: Operating System :: OS Independent
Classifier: Topic :: Software Development :: Libraries :: Python Modules
Classifier: Topic :: Scientific/Engineering :: Mathematics
Requires-Dist: numpy
